{
  "libraryTrack": {
    "__typename": "LibraryTrack",
    "id": "27639522",
    "title": "Cozy Dreams.mp3",
    "audioAnalysisV7": {
      "__typename": "AudioAnalysisV7Finished",
      "result": {
        "valence": -0.45483236823742057,
        "arousal": -0.4418966554933124,
        "energyLevel": "low",
        "energyDynamics": "low",
        "emotionalProfile": "negative",
        "emotionalDynamics": "low",
        "voicePresenceProfile": "none",
        "predominantVoiceGender": "none",
        "voice": {
          "female": 0.010627699168657677,
          "male": 0.027168338290519185,
          "instrumental": 0.9525011049376594
        },
        "voiceTags": [
          "instrumental"
        ],
        "musicalEraTag": "late 2000s / contemporary",
        "classicalEpochTags": null,
        "classicalEpoch": null,
        "instrumentPresence": {
          "percussion": "absent",
          "synth": "absent",
          "piano": "absent",
          "acousticGuitar": "absent",
          "electricGuitar": "frequently",
          "strings": "absent",
          "bass": "absent",
          "bassGuitar": "absent",
          "brassWoodwinds": "absent"
        },
        "advancedInstrumentPresence": {
          "percussion": "absent",
          "synth": "absent",
          "piano": "absent",
          "acousticGuitar": "absent",
          "electricGuitar": "frequently",
          "strings": "absent",
          "bass": "absent",
          "bassGuitar": "absent",
          "brass": "absent",
          "woodwinds": "absent"
        },
        "advancedInstrumentPresenceExtended": {
          "acousticGuitar": "absent",
          "bass": "absent",
          "bassGuitar": "absent",
          "electricGuitar": "frequently",
          "percussion": "absent",
          "piano": "absent",
          "synth": "absent",
          "strings": "absent",
          "brass": "absent",
          "woodwinds": "absent",
          "tuba": "absent",
          "frenchHorn": "absent",
          "oboe": "absent",
          "mandolin": "absent",
          "cello": "absent",
          "marimba": "absent",
          "vibraphone": "absent",
          "electricPiano": "absent",
          "electricOrgan": "absent",
          "harp": "absent",
          "ukulele": "absent",
          "harpsichord": "absent",
          "churchOrgan": "absent",
          "doubleBass": "absent",
          "glockenspiel": "absent",
          "electronicDrums": "absent",
          "drumKit": "absent",
          "accordion": "absent",
          "violin": "absent",
          "flute": "absent",
          "sax": "absent",
          "trumpet": "absent",
          "celeste": "absent",
          "pizzicato": "absent",
          "banjo": "absent",
          "clarinet": "absent",
          "bells": "absent",
          "steelDrums": "absent",
          "bongoConga": "absent",
          "africanPercussion": "absent",
          "tabla": "absent",
          "sitar": "absent",
          "taiko": "absent",
          "asianFlute": "absent",
          "asianStrings": "absent",
          "luteOud": "absent"
        },
        "instrumentTags": [
          "electricGuitar"
        ],
        "advancedInstrumentTags": [
          "electricGuitar"
        ],
        "advancedInstrumentTagsExtended": [
          "electricGuitar"
        ],
        "mood": {
          "aggressive": 0.07192400635944472,
          "calm": 0.5368409686618381,
          "chilled": 0.3889137837621901,
          "dark": 0.2808017349905438,
          "energetic": 0.0949443131685257,
          "epic": 0.027795570799046092,
          "happy": 0.11330143155323134,
          "romantic": 0.34981335865126717,
          "sad": 0.5599691006872389,
          "scary": 0.08985636093550259,
          "sexy": 0.09044026086727779,
          "ethereal": 0.30831364128324723,
          "uplifting": 0.0923154428601265
        },
        "moodTags": [
          "sad",
          "calm",
          "chilled"
        ],
        "moodAdvanced": {
          "anxious": 0.10461107393105824,
          "barren": 0.2469067151347796,
          "cold": 0.1007580893735091,
          "creepy": 0.04689235074652566,
          "dark": 0.09338227245542738,
          "disturbing": 0.056657239173849426,
          "eerie": 0.08204752869076198,
          "evil": 0.035109553693069354,
          "fearful": 0.038116145672069654,
          "mysterious": 0.33511663642194534,
          "nervous": 0.11183720495965746,
          "restless": 0.12331302381224102,
          "spooky": 0.0766717866063118,
          "strange": 0.14203291055228975,
          "supernatural": 0.061349371862080365,
          "suspenseful": 0.12455643961826961,
          "tense": 0.08289001468155119,
          "weird": 0.1995537198252148,
          "aggressive": 0.01249082867677013,
          "agitated": 0.024434776976704597,
          "angry": 0.00543011792211069,
          "dangerous": 0.03932609077956942,
          "fiery": 0.01442275708541274,
          "intense": 0.0585029311478138,
          "passionate": 0.10217497870326042,
          "ponderous": 0.1084390746222602,
          "violent": 0.01015633096297582,
          "comedic": 0.04349344244433774,
          "eccentric": 0.040666383794612355,
          "funny": 0.025248020163012877,
          "mischievous": 0.035495316713220544,
          "quirky": 0.08370524562067455,
          "whimsical": 0.052569341742330127,
          "boisterous": 0.023555013144181833,
          "boingy": 0.0233748329596387,
          "bright": 0.05766157598959075,
          "celebratory": 0.013765918039199378,
          "cheerful": 0.03448244432608286,
          "excited": 0.019142510576380625,
          "feelGood": 0.06662928519977464,
          "fun": 0.02762202059643136,
          "happy": 0.03306632654534446,
          "joyous": 0.018644068390130997,
          "lighthearted": 0.05794488431678878,
          "perky": 0.03338139752546946,
          "playful": 0.04582082045574983,
          "rollicking": 0.021793303183383413,
          "upbeat": 0.0493454999393887,
          "calm": 0.32312073972490096,
          "contented": 0.20599589579635197,
          "dreamy": 0.36883044573995805,
          "introspective": 0.48948681023385787,
          "laidBack": 0.29509324663215214,
          "leisurely": 0.29502107037438285,
          "lyrical": 0.08162147924304008,
          "peaceful": 0.3189803378449546,
          "quiet": 0.2777293291356828,
          "relaxed": 0.46590646107991535,
          "serene": 0.34883371161090004,
          "soothing": 0.1957812723186281,
          "spiritual": 0.19217489825354683,
          "tranquil": 0.2864525963862737,
          "bittersweet": 0.49821019503805375,
          "blue": 0.4595114373498493,
          "depressing": 0.20761460893683964,
          "gloomy": 0.17913063946697447,
          "heavy": 0.14986374146408504,
          "lonely": 0.5064484708838992,
          "melancholic": 0.4535176820225186,
          "mournful": 0.28492846257156795,
          "poignant": 0.2354230433702469,
          "sad": 0.30785983469751144,
          "frightening": 0.029681866988539696,
          "horror": 0.01450389028630323,
          "menacing": 0.09329337543911403,
          "nightmarish": 0.01789418276813295,
          "ominous": 0.10057456998361482,
          "panicStricken": 0.007726413896307349,
          "scary": 0.026013381572233304,
          "concerned": 0.19768114222420585,
          "determined": 0.08256805646750662,
          "dignified": 0.046991920098662376,
          "emotional": 0.20648705628183153,
          "noble": 0.029272989990810554,
          "serious": 0.2789797567658954,
          "solemn": 0.10000184675057729,
          "thoughtful": 0.40507646401723224,
          "cool": 0.0503926347527239,
          "seductive": 0.09541666011015575,
          "sexy": 0.05074730639656385,
          "adventurous": 0.020477450038823817,
          "confident": 0.09555311252673467,
          "courageous": 0.015267577798416218,
          "resolute": 0.06374190251032512,
          "energetic": 0.026314879560636148,
          "epic": 0.01119653270062473,
          "exciting": 0.02250227714992232,
          "exhilarating": 0.01994910453342729,
          "heroic": 0.007306204229179356,
          "majestic": 0.008979556538785497,
          "powerful": 0.019931521991060838,
          "prestigious": 0.011830415473216109,
          "relentless": 0.04173019611173206,
          "strong": 0.0264384253985352,
          "triumphant": 0.008094588191144995,
          "victorious": 0.008381354441452358,
          "delicate": 0.16182317170831892,
          "graceful": 0.07213911786675453,
          "hopeful": 0.11289098072383139,
          "innocent": 0.0970633298986488,
          "intimate": 0.23455499278174508,
          "kind": 0.06790295491615932,
          "light": 0.21380958788924748,
          "loving": 0.11577814237938987,
          "nostalgic": 0.357944024933709,
          "reflective": 0.40051232112778556,
          "romantic": 0.11335902950829929,
          "sentimental": 0.1834507534901301,
          "soft": 0.14943748629755443,
          "sweet": 0.07452816681729423,
          "tender": 0.1655290267533726,
          "warm": 0.2639836155705982,
          "anthemic": 0.010643419499198595,
          "aweInspiring": 0.019856631238427427,
          "euphoric": 0.010877447202801704,
          "inspirational": 0.04380870796740055,
          "motivational": 0.028429138681126967,
          "optimistic": 0.06976494979527262,
          "positive": 0.08669258116020097,
          "proud": 0.03754687516225709,
          "soaring": 0.03663672424025006,
          "uplifting": 0.04710758622321817
        },
        "moodAdvancedTags": [
          "lonely",
          "bittersweet",
          "introspective",
          "relaxed",
          "blue"
        ],
        "genre": {
          "ambient": 0.13539066331254113,
          "blues": 0.09027265643493997,
          "classical": 0.008939723173777262,
          "electronicDance": 0.02674174660609828,
          "folkCountry": 0.017747464848475322,
          "funkSoul": 0.008922768291085958,
          "jazz": 0.0412532270161642,
          "latin": 0.011459174514230754,
          "metal": 0.020409396306301158,
          "pop": 0.056154835555288524,
          "rapHipHop": 0.014468338754442003,
          "reggae": 0.014675400944219695,
          "rnb": 0.02363484042386214,
          "rock": 0.07763904188242224,
          "singerSongwriter": 0.03320517328878244
        },
        "genreTags": [
          "ambient"
        ],
        "advancedGenre": {
          "afro": 0.027473336551338434,
          "ambient": 0.13539066331254113,
          "arab": 0.013435811994390355,
          "asian": 0.029917525127530098,
          "blues": 0.09027265643493997,
          "childrenJingle": 0.03219959636529287,
          "classical": 0.008939723173777262,
          "electronicDance": 0.02674174660609828,
          "folkCountry": 0.017747464848475322,
          "funkSoul": 0.008922768291085958,
          "indian": 0.004837335203774273,
          "jazz": 0.0412532270161642,
          "latin": 0.011459174514230754,
          "metal": 0.020409396306301158,
          "pop": 0.056154835555288524,
          "rapHipHop": 0.014468338754442003,
          "reggae": 0.014675400944219695,
          "rnb": 0.02363484042386214,
          "rock": 0.07763904188242224,
          "singerSongwriters": 0.03320517328878244,
          "sound": 0.04463272127840254,
          "soundtrack": 0.21375648511780632,
          "spokenWord": 0.0033776807443549237
        },
        "advancedGenreTags": [
          "soundtrack",
          "ambient"
        ],
        "subgenre": {
          "bluesRock": null,
          "folkRock": null,
          "hardRock": null,
          "indieAlternative": null,
          "psychedelicProgressiveRock": null,
          "punk": null,
          "rockAndRoll": null,
          "popSoftRock": null,
          "abstractIDMLeftfield": null,
          "breakbeatDnB": null,
          "deepHouse": null,
          "electro": null,
          "house": null,
          "minimal": null,
          "synthPop": null,
          "techHouse": null,
          "techno": null,
          "trance": null,
          "contemporaryRnB": null,
          "gangsta": null,
          "jazzyHipHop": null,
          "popRap": null,
          "trap": null,
          "blackMetal": null,
          "deathMetal": null,
          "doomMetal": null,
          "heavyMetal": null,
          "metalcore": null,
          "nuMetal": null,
          "disco": null,
          "funk": null,
          "gospel": null,
          "neoSoul": null,
          "soul": null,
          "bigBandSwing": null,
          "bebop": null,
          "contemporaryJazz": null,
          "easyListening": null,
          "fusion": null,
          "latinJazz": null,
          "smoothJazz": null,
          "country": null,
          "folk": null
        },
        "subgenreTags": [],
        "advancedSubgenre": {
          "bluesRock": null,
          "folkRock": null,
          "hardRock": null,
          "indieAlternative": null,
          "psychedelicProgressiveRock": null,
          "punk": null,
          "rockAndRoll": null,
          "popSoftRock": null,
          "abstractIDMLeftfield": null,
          "breakbeatDnB": null,
          "deepHouse": null,
          "electro": null,
          "house": null,
          "minimal": null,
          "synthPop": null,
          "techHouse": null,
          "techno": null,
          "trance": null,
          "contemporaryRnB": null,
          "gangsta": null,
          "jazzyHipHop": null,
          "popRap": null,
          "trap": null,
          "blackMetal": null,
          "deathMetal": null,
          "doomMetal": null,
          "heavyMetal": null,
          "metalcore": null,
          "nuMetal": null,
          "disco": null,
          "funk": null,
          "gospel": null,
          "neoSoul": null,
          "soul": null,
          "bigBandSwing": null,
          "bebop": null,
          "contemporaryJazz": null,
          "easyListening": null,
          "fusion": null,
          "latinJazz": null,
          "smoothJazz": null,
          "country": null,
          "folk": null
        },
        "advancedSubgenreTags": [],
        "movement": {
          "bouncy": 0.05120670795440674,
          "driving": 0.07783983275294304,
          "flowing": 0.38599447243743473,
          "groovy": 0.052707054962714515,
          "nonrhythmic": 0.10291176786025365,
          "pulsing": 0.10965122779210408,
          "robotic": 0.07141051606999503,
          "running": 0.06815393558806843,
          "steady": 0.4191506968604194,
          "stomping": 0.06914016604423523
        },
        "movementTags": [
          "steady",
          "flowing"
        ],
        "character": {
          "bold": 0.08574552668465509,
          "cool": 0.17059005465772417,
          "epic": 0.023482099796334904,
          "ethereal": 0.29424140188429093,
          "heroic": 0.025866506310800712,
          "luxurious": 0.05835016671982077,
          "magical": 0.07128536473545763,
          "mysterious": 0.2626184556219313,
          "playful": 0.11167856740454833,
          "powerful": 0.020213513842059508,
          "retro": 0.2312098890542984,
          "sophisticated": 0.06074387228323354,
          "sparkling": 0.08247637500365575,
          "sparse": 0.4148554239008162,
          "unpolished": 0.11189715315898259,
          "warm": 0.21420268383291033
        },
        "characterTags": [
          "sparse"
        ],
        "transformerCaption": "slow, bluesy electric guitar solo with reverb.",
        "freeGenreTags": "indie, indie folk, singer-songwriter",
        "voiceoverDegree": null,
        "voiceoverExists": false,
        "bpmPrediction": {
          "value": 100,
          "confidence": 0.32285688811657476
        },
        "bpmRangeAdjusted": 100,
        "keyPrediction": {
          "value": "gMajor",
          "confidence": 0.6362594314243483
        },
        "timeSignature": "4/4",
        "segments": {
          "representativeSegmentIndex": 5,
          "timestamps": [
            15,
            30,
            45,
            60,
            75,
            90,
            105,
            120,
            135
          ],
          "mood": {
            "aggressive": [
              0.06567894667387009,
              0.07830673456192017,
              0.04786010459065437,
              0.04951408877968788,
              0.07425221055746078,
              0.04763573780655861,
              0.056407757103443146,
              0.1210281178355217,
              0.10663235932588577
            ],
            "calm": [
              0.6272540092468262,
              0.460149347782135,
              0.5716707110404968,
              0.5142459869384766,
              0.5234330892562866,
              0.6255400776863098,
              0.5403757095336914,
              0.45615154504776,
              0.5127482414245605
            ],
            "chilled": [
              0.4014759957790375,
              0.3519171476364136,
              0.39718466997146606,
              0.4376174807548523,
              0.31433868408203125,
              0.44611087441444397,
              0.44871631264686584,
              0.3524993062019348,
              0.3503635823726654
            ],
            "dark": [
              0.18722990155220032,
              0.16455614566802979,
              0.23995311558246613,
              0.3205774128437042,
              0.5117957592010498,
              0.2997969686985016,
              0.2586170434951782,
              0.2585129737854004,
              0.28617629408836365
            ],
            "energetic": [
              0.08255312591791153,
              0.1529741883277893,
              0.05908098816871643,
              0.06751956790685654,
              0.09195979684591293,
              0.06319497525691986,
              0.08644446730613708,
              0.1374908685684204,
              0.11328084021806717
            ],
            "epic": [
              0.020944934338331223,
              0.04120228439569473,
              0.00956870336085558,
              0.018291611224412918,
              0.015498469583690166,
              0.029777079820632935,
              0.03075808472931385,
              0.04125203564763069,
              0.04286693409085274
            ],
            "happy": [
              0.08827916532754898,
              0.10542777925729752,
              0.04703044518828392,
              0.1017141118645668,
              0.06699690967798233,
              0.08854053169488907,
              0.19527143239974976,
              0.18642672896385193,
              0.1400257796049118
            ],
            "romantic": [
              0.35281145572662354,
              0.3504522740840912,
              0.43230217695236206,
              0.29476991295814514,
              0.1894729733467102,
              0.3198467791080475,
              0.34489619731903076,
              0.4022914469242096,
              0.46147701144218445
            ],
            "sad": [
              0.654082715511322,
              0.5488693714141846,
              0.7104163765907288,
              0.5600796937942505,
              0.5971567630767822,
              0.6466803550720215,
              0.523138165473938,
              0.37151509523391724,
              0.42778337001800537
            ],
            "scary": [
              0.049509450793266296,
              0.04135952517390251,
              0.04678335040807724,
              0.09287208318710327,
              0.17376932501792908,
              0.09101303666830063,
              0.0866149291396141,
              0.1120026558637619,
              0.1147828921675682
            ],
            "sexy": [
              0.07695597410202026,
              0.07916721701622009,
              0.061767321079969406,
              0.09838700294494629,
              0.06050107255578041,
              0.08846914768218994,
              0.11850932985544205,
              0.11917517334222794,
              0.11103010922670364
            ],
            "ethereal": [
              0.31733438372612,
              0.2483975887298584,
              0.26496490836143494,
              0.2596092224121094,
              0.3512011468410492,
              0.4446071982383728,
              0.3332657516002655,
              0.2541021704673767,
              0.30134040117263794
            ],
            "uplifting": [
              0.08383981138467789,
              0.1331811547279358,
              0.04377994313836098,
              0.0683705285191536,
              0.05703553184866905,
              0.08727093786001205,
              0.11484094709157944,
              0.1291421353816986,
              0.11337799578905106
            ]
          },
          "voice": {
            "female": [
              0.0007066818652674556,
              0.0022215773351490498,
              0.0004908895934931934,
              0.0009387123864144087,
              0.004396670497953892,
              0.00957206729799509,
              0.021601296961307526,
              0.032224033027887344,
              0.023497363552451134
            ],
            "instrumental": [
              0.9925432205200195,
              0.9558558464050293,
              0.9939082860946655,
              0.9917131662368774,
              0.9826529026031494,
              0.8878624439239502,
              0.9169524908065796,
              0.9082674980163574,
              0.9427540898323059
            ],
            "male": [
              0.00863674096763134,
              0.04233890771865845,
              0.007791866548359394,
              0.008950520306825638,
              0.012303591705858707,
              0.0752183273434639,
              0.03401650860905647,
              0.034093357622623444,
              0.02116522379219532
            ]
          },
          "instruments": {
            "percussion": [
              0.2000732123851776,
              0.25098857283592224,
              0.12061399221420288,
              0.03527087718248367,
              0.27025842666625977,
              0.15817420184612274,
              0.08797121047973633,
              0.10144592076539993,
              0.0873691588640213
            ],
            "synth": [
              0.008646572940051556,
              0.04938768967986107,
              0.017118461430072784,
              0.04956239461898804,
              0.23276792466640472,
              0.22071495652198792,
              0.27216604351997375,
              0.2399887889623642,
              0.37660303711891174
            ],
            "piano": [
              0.014970807358622551,
              0.048079002648591995,
              0.021415913477540016,
              0.06135329604148865,
              0.085738405585289,
              0.07768938690423965,
              0.0931268110871315,
              0.3002258837223053,
              0.18334358930587769
            ],
            "acousticGuitar": [
              0.38582324981689453,
              0.2248421013355255,
              0.26001742482185364,
              0.3015648126602173,
              0.3034449815750122,
              0.4031819999217987,
              0.13786138594150543,
              0.11321499943733215,
              0.14497265219688416
            ],
            "electricGuitar": [
              0.8191383481025696,
              0.8985996246337891,
              0.7541729807853699,
              0.5386509895324707,
              0.7558140158653259,
              0.7273327708244324,
              0.5620105266571045,
              0.4887826144695282,
              0.23278911411762238
            ],
            "strings": [
              0.036385733634233475,
              0.10296827554702759,
              0.02300792559981346,
              0.023863298818469048,
              0.09131446480751038,
              0.12634076178073883,
              0.057758886367082596,
              0.06889984011650085,
              0.14019937813282013
            ],
            "bass": [
              0.008664974942803383,
              0.01857505366206169,
              0.009406136348843575,
              0.008583093993365765,
              0.07664135098457336,
              0.0240486990660429,
              0.011178814806044102,
              0.02443034201860428,
              0.020217908546328545
            ],
            "bassGuitar": [
              0.07911346852779388,
              0.30168238282203674,
              0.05507125332951546,
              0.03965279087424278,
              0.41651561856269836,
              0.4299851655960083,
              0.10232832282781601,
              0.10077685117721558,
              0.2492433488368988
            ],
            "brassWoodwinds": [
              0.03176798298954964,
              0.2009693831205368,
              0.04216920956969261,
              0.049891091883182526,
              0.044138237833976746,
              0.08192668110132217,
              0.18323063850402832,
              0.06339649111032486,
              0.11792308837175369
            ]
          },
          "genre": {
            "ambient": [
              0.0886097252368927,
              0.0932568684220314,
              0.12053246051073074,
              0.10159192979335785,
              0.14258649945259094,
              0.09795018285512924,
              0.17546717822551727,
              0.204204723238945,
              0.19431640207767487
            ],
            "blues": [
              0.1908935308456421,
              0.13467206060886383,
              0.1656801700592041,
              0.1409970223903656,
              0.0435154102742672,
              0.08264710009098053,
              0.033643707633018494,
              0.0067154113203287125,
              0.01368949469178915
            ],
            "classical": [
              0.0069238352589309216,
              0.006037372164428234,
              0.004596030805259943,
              0.006432394962757826,
              0.007973004132509232,
              0.008808113634586334,
              0.007074342574924231,
              0.007611136883497238,
              0.025001278147101402
            ],
            "electronicDance": [
              0.01323397271335125,
              0.020124472677707672,
              0.025929320603609085,
              0.034682586789131165,
              0.03830472379922867,
              0.03422325849533081,
              0.026116181164979935,
              0.024471815675497055,
              0.02358938753604889
            ],
            "folkCountry": [
              0.03202470764517784,
              0.025675568729639053,
              0.03915968909859657,
              0.01967470906674862,
              0.008045227266848087,
              0.01836506277322769,
              0.008606457151472569,
              0.003559849224984646,
              0.004615912679582834
            ],
            "funkSoul": [
              0.007186259608715773,
              0.01048548799008131,
              0.01148343738168478,
              0.015581084415316582,
              0.01003361027687788,
              0.016710959374904633,
              0.003764242632314563,
              0.001300040865316987,
              0.003759792074561119
            ],
            "jazz": [
              0.04349079355597496,
              0.04656728729605675,
              0.04967837035655975,
              0.06361283361911774,
              0.04190176725387573,
              0.05417816340923309,
              0.030488887801766396,
              0.00962082203477621,
              0.03174011781811714
            ],
            "latin": [
              0.007903882302343845,
              0.011366749182343483,
              0.014510627835988998,
              0.01759251207113266,
              0.01116170547902584,
              0.020769905298948288,
              0.009494033642113209,
              0.0034926366060972214,
              0.006840518210083246
            ],
            "metal": [
              0.03775075823068619,
              0.02223924733698368,
              0.027762800455093384,
              0.02469937689602375,
              0.02431519329547882,
              0.0359027162194252,
              0.0045585124753415585,
              0.003276696428656578,
              0.003179265419021249
            ],
            "pop": [
              0.04274794086813927,
              0.06135447695851326,
              0.06622256338596344,
              0.08957884460687637,
              0.05810963362455368,
              0.1031695082783699,
              0.04247047379612923,
              0.022167835384607315,
              0.019572243094444275
            ],
            "rapHipHop": [
              0.0094448272138834,
              0.013362829573452473,
              0.013869909569621086,
              0.022531021386384964,
              0.01436736062169075,
              0.025636659935116768,
              0.01253443956375122,
              0.012184605933725834,
              0.006283394992351532
            ],
            "reggae": [
              0.010475369170308113,
              0.011940613389015198,
              0.018105236813426018,
              0.024109479039907455,
              0.013483952730894089,
              0.02881018817424774,
              0.011019628494977951,
              0.006540170405060053,
              0.007593970280140638
            ],
            "rnb": [
              0.01279677264392376,
              0.023812362924218178,
              0.022229701280593872,
              0.03298833966255188,
              0.026354622095823288,
              0.04173976555466652,
              0.020237140357494354,
              0.020700905472040176,
              0.011853953823447227
            ],
            "rock": [
              0.08422646671533585,
              0.0887971818447113,
              0.10292079299688339,
              0.13658885657787323,
              0.07693082094192505,
              0.13189491629600525,
              0.04038536176085472,
              0.01781228370964527,
              0.019194696098566055
            ],
            "singerSongwriter": [
              0.025019023567438126,
              0.031927790492773056,
              0.0354364849627018,
              0.06979166716337204,
              0.03674550727009773,
              0.05478280037641525,
              0.020585907623171806,
              0.008923402056097984,
              0.015633976086974144
            ]
          },
          "subgenre": {
            "bluesRock": null,
            "folkRock": null,
            "hardRock": null,
            "indieAlternative": null,
            "psychedelicProgressiveRock": null,
            "punk": null,
            "rockAndRoll": null,
            "popSoftRock": null,
            "abstractIDMLeftfield": null,
            "breakbeatDnB": null,
            "deepHouse": null,
            "electro": null,
            "house": null,
            "minimal": null,
            "synthPop": null,
            "techHouse": null,
            "techno": null,
            "trance": null,
            "contemporaryRnB": null,
            "gangsta": null,
            "jazzyHipHop": null,
            "popRap": null,
            "trap": null,
            "blackMetal": null,
            "deathMetal": null,
            "doomMetal": null,
            "heavyMetal": null,
            "metalcore": null,
            "nuMetal": null,
            "disco": null,
            "funk": null,
            "gospel": null,
            "neoSoul": null,
            "soul": null,
            "bigBandSwing": null,
            "bebop": null,
            "contemporaryJazz": null,
            "easyListening": null,
            "fusion": null,
            "latinJazz": null,
            "smoothJazz": null,
            "country": null,
            "folk": null
          },
          "valence": [
            -0.508921479712341,
            -0.376913391297306,
            -0.672744211173559,
            -0.492733937471929,
            -0.667923482724736,
            -0.519292451494854,
            -0.283288864859318,
            -0.233075128274066,
            -0.338598367128676
          ],
          "arousal": [
            -0.544700883328915,
            -0.307175159454346,
            -0.51258972287178,
            -0.44672641903162,
            -0.431473292410374,
            -0.56234510242939,
            -0.453931242227554,
            -0.31866067647934,
            -0.399467401206493
          ],
          "classicalEpoch": null,
          "character": {
            "bold": [
              0.116025596857071,
              0.154218420386314,
              0.109365493059158,
              0.0959712117910385,
              0.0533619560301304,
              0.0505625940859318,
              0.0426030829548836,
              0.0805251076817513,
              0.0690762773156166
            ],
            "cool": [
              0.251380681991577,
              0.163433820009232,
              0.193512871861458,
              0.196906134486198,
              0.103580743074417,
              0.191337615251541,
              0.136718824505806,
              0.162593796849251,
              0.135846003890038
            ],
            "epic": [
              0.013152320869267,
              0.0529892183840275,
              0.0169980935752392,
              0.00413187500089407,
              0.0147229991853237,
              0.0153185902163386,
              0.0110207153484225,
              0.0353763327002525,
              0.047628752887249
            ],
            "ethereal": [
              0.314460694789886,
              0.233623549342155,
              0.300625950098038,
              0.279020965099335,
              0.382277935743332,
              0.41579407453537,
              0.24174328148365,
              0.211646646261215,
              0.268979519605637
            ],
            "heroic": [
              0.0280840266495943,
              0.0394795089960098,
              0.0109499171376228,
              0.00866955798119307,
              0.0104938764125109,
              0.0156596079468727,
              0.0171953439712524,
              0.0487258099019527,
              0.0535409078001976
            ],
            "luxurious": [
              0.0391397140920162,
              0.0423330143094063,
              0.0306084919720888,
              0.0517648048698902,
              0.0416234210133553,
              0.0661381483078003,
              0.0770847648382187,
              0.079383410513401,
              0.0970757305622101
            ],
            "magical": [
              0.055143229663372,
              0.0408846661448479,
              0.0206712055951357,
              0.0175323039293289,
              0.053168773651123,
              0.0600910112261772,
              0.0771775841712952,
              0.15197466313839,
              0.164924845099449
            ],
            "mysterious": [
              0.211387634277344,
              0.18736332654953,
              0.22992704808712,
              0.263195097446442,
              0.471628874540329,
              0.243262082338333,
              0.240940615534782,
              0.2297343313694,
              0.286127090454102
            ],
            "playful": [
              0.0934561491012573,
              0.0493186414241791,
              0.0208394471555948,
              0.0699058100581169,
              0.0831088051199913,
              0.0740682110190392,
              0.235900297760963,
              0.224096670746803,
              0.15441307425499
            ],
            "powerful": [
              0.0125322910025716,
              0.04287975654006,
              0.0129120806232095,
              0.00649342872202396,
              0.0136182829737663,
              0.0114081241190434,
              0.0119656668975949,
              0.0345911271870136,
              0.0355208665132523
            ],
            "retro": [
              0.202009558677673,
              0.273411124944687,
              0.362970560789108,
              0.372001618146896,
              0.0894946902990341,
              0.237298294901848,
              0.271337747573853,
              0.136048659682274,
              0.136316746473312
            ],
            "sophisticated": [
              0.0283630155026913,
              0.042170450091362,
              0.0307833794504404,
              0.0514506436884403,
              0.0336970910429955,
              0.0498503409326077,
              0.0824941843748093,
              0.109541095793247,
              0.118344649672508
            ],
            "sparkling": [
              0.0246604923158884,
              0.0614797025918961,
              0.024792218580842,
              0.0357825271785259,
              0.102289035916328,
              0.0858564004302025,
              0.14981971681118,
              0.129004567861557,
              0.128602713346481
            ],
            "sparse": [
              0.309544861316681,
              0.385107785463333,
              0.651662886142731,
              0.527481973171234,
              0.649894297122955,
              0.582040786743164,
              0.240502908825874,
              0.183605402708054,
              0.203857913613319
            ],
            "unpolished": [
              0.143363296985626,
              0.184952050447464,
              0.137273088097572,
              0.0683669522404671,
              0.138427257537842,
              0.0818063169717789,
              0.0469334125518799,
              0.101835444569588,
              0.104116559028625
            ],
            "warm": [
              0.256541699171066,
              0.234280318021774,
              0.235264182090759,
              0.17192716896534,
              0.130320817232132,
              0.265152782201767,
              0.187934994697571,
              0.212734863162041,
              0.233667328953743
            ]
          },
          "movement": {
            "bouncy": [
              0.0503497608006001,
              0.0405528284609318,
              0.0175506807863712,
              0.0627026632428169,
              0.0282198712229729,
              0.0391675755381584,
              0.0851518735289574,
              0.0875533297657967,
              0.0496117882430553
            ],
            "driving": [
              0.075466200709343,
              0.130566954612732,
              0.0705037862062454,
              0.0914715975522995,
              0.0491404645144939,
              0.0588531978428364,
              0.0848343595862389,
              0.081362709403038,
              0.0583592243492603
            ],
            "flowing": [
              0.475331783294678,
              0.391808837652206,
              0.362295806407928,
              0.215705350041389,
              0.318461805582047,
              0.455289572477341,
              0.383729666471481,
              0.386761635541916,
              0.484565794467926
            ],
            "groovy": [
              0.0343111231923103,
              0.0457688383758068,
              0.0491880066692829,
              0.08989267796278,
              0.0627875700592995,
              0.0499100759625435,
              0.0506196469068527,
              0.0531750880181789,
              0.0387104675173759
            ],
            "nonrhythmic": [
              0.0754183381795883,
              0.0604214482009411,
              0.0517735183238983,
              0.100092627108097,
              0.0370454303920269,
              0.123167686164379,
              0.142856046557426,
              0.146083563566208,
              0.189347252249718
            ],
            "pulsing": [
              0.0740043446421623,
              0.071653850376606,
              0.0836951732635498,
              0.10591571778059,
              0.229514226317406,
              0.162479549646378,
              0.105714477598667,
              0.0904063135385513,
              0.0634773969650269
            ],
            "robotic": [
              0.033206969499588,
              0.0425579883158207,
              0.0376523919403553,
              0.0753566697239876,
              0.137091591954231,
              0.0839978232979774,
              0.081193782389164,
              0.0786115303635597,
              0.0730258971452713
            ],
            "running": [
              0.0596643164753914,
              0.118667468428612,
              0.0708053931593895,
              0.0595953762531281,
              0.0602156184613705,
              0.0357158742845058,
              0.0569033585488796,
              0.0798878446221352,
              0.0719301700592041
            ],
            "steady": [
              0.32594758272171,
              0.455014050006866,
              0.595877945423126,
              0.523542702198029,
              0.410263329744339,
              0.459872484207153,
              0.426786512136459,
              0.278871297836304,
              0.296180367469788
            ],
            "stomping": [
              0.0895175114274025,
              0.0949936509132385,
              0.054661501199007,
              0.111253701150417,
              0.0423878468573093,
              0.0691755637526512,
              0.0509546101093292,
              0.0566389933228493,
              0.0526781156659126
            ]
          },
          "moodAdvanced": {
            "anxious": [
              0.0563449189066887,
              0.068297803401947,
              0.115524969995022,
              0.118387565016747,
              0.215546309947968,
              0.10421234369278,
              0.0945396423339844,
              0.0806487128138542,
              0.0879973992705345
            ],
            "barren": [
              0.241081342101097,
              0.167506486177444,
              0.420731872320175,
              0.272254884243011,
              0.337036579847336,
              0.337548345327377,
              0.159687742590904,
              0.121653236448765,
              0.164659947156906
            ],
            "cold": [
              0.0467037968337536,
              0.0739157348871231,
              0.102911062538624,
              0.0845105350017548,
              0.205950692296028,
              0.143079489469528,
              0.0819524526596069,
              0.0749960243701935,
              0.0928030163049698
            ],
            "creepy": [
              0.0236994847655296,
              0.0320487283170223,
              0.035772580653429,
              0.043564110994339,
              0.0757574364542961,
              0.0522898212075233,
              0.0383753478527069,
              0.0531822666525841,
              0.0673413798213005
            ],
            "dark": [
              0.0435358658432961,
              0.0800455659627914,
              0.119271799921989,
              0.0769096240401268,
              0.198121607303619,
              0.111858025193214,
              0.0487921386957169,
              0.0680915862321854,
              0.0938142389059067
            ],
            "disturbing": [
              0.025029631331563,
              0.0442976132035255,
              0.0589144676923752,
              0.0569909140467644,
              0.107012711465359,
              0.0635509118437767,
              0.0375407859683037,
              0.0496536269783974,
              0.0669244900345802
            ],
            "eerie": [
              0.0303920917212963,
              0.0457849577069283,
              0.0584835670888424,
              0.0673938915133476,
              0.16203086078167,
              0.0964121893048286,
              0.0801685005426407,
              0.0850077494978905,
              0.112753950059414
            ],
            "evil": [
              0.0135894045233727,
              0.0260994862765074,
              0.0360900573432446,
              0.027318736538291,
              0.0795381292700768,
              0.0435210019350052,
              0.0214451923966408,
              0.0296398047357798,
              0.0387441702187061
            ],
            "fearful": [
              0.0231258515268564,
              0.0230547301471233,
              0.0351367369294167,
              0.0315713621675968,
              0.0892480835318565,
              0.0400362238287926,
              0.0272138230502605,
              0.0329744704067707,
              0.0406840294599533
            ],
            "mysterious": [
              0.233447626233101,
              0.228417217731476,
              0.344902187585831,
              0.342660635709763,
              0.547898888587952,
              0.394842594861984,
              0.327955305576324,
              0.26709109544754,
              0.328834176063538
            ],
            "nervous": [
              0.0849915966391563,
              0.090732254087925,
              0.098270907998085,
              0.0937167406082153,
              0.215344563126564,
              0.0808047503232956,
              0.0927983820438385,
              0.125234797596931,
              0.124640852212906
            ],
            "restless": [
              0.120728828012943,
              0.105936609208584,
              0.116435945034027,
              0.102838136255741,
              0.226909697055817,
              0.0929747894406319,
              0.101512089371681,
              0.120202876627445,
              0.122278243303299
            ],
            "spooky": [
              0.0289757661521435,
              0.0477638803422451,
              0.0540955141186714,
              0.0759493261575699,
              0.119872778654099,
              0.0887622237205505,
              0.0674855709075928,
              0.0907079502940178,
              0.116433069109917
            ],
            "strange": [
              0.0686139911413193,
              0.074695959687233,
              0.124207057058811,
              0.163230717182159,
              0.234615489840508,
              0.167674735188484,
              0.156291887164116,
              0.14030958712101,
              0.148656770586967
            ],
            "supernatural": [
              0.0171029847115278,
              0.0337078161537647,
              0.0382250249385834,
              0.0370477698743343,
              0.124095119535923,
              0.0835526585578918,
              0.0562585815787315,
              0.0671562701463699,
              0.0949981212615967
            ],
            "suspenseful": [
              0.0901145115494728,
              0.0748536586761475,
              0.128427863121033,
              0.113409742712975,
              0.290888607501984,
              0.116036735475063,
              0.100125923752785,
              0.0968166366219521,
              0.110334277153015
            ],
            "tense": [
              0.0405153036117554,
              0.062310453504324,
              0.086141973733902,
              0.0775410979986191,
              0.214320212602615,
              0.0739242285490036,
              0.0555582083761692,
              0.0634037852287292,
              0.0722948685288429
            ],
            "weird": [
              0.101329237222672,
              0.0994696468114853,
              0.167931720614433,
              0.279961794614792,
              0.309201508760452,
              0.259015172719955,
              0.237734794616699,
              0.172180771827698,
              0.169158831238747
            ],
            "aggressive": [
              0.00651459256187081,
              0.0151816895231605,
              0.0102187786251307,
              0.00644147535786033,
              0.0114375567063689,
              0.00655621476471424,
              0.00621171528473496,
              0.0257753469049931,
              0.0240800883620977
            ],
            "agitated": [
              0.0257130619138479,
              0.0246211029589176,
              0.0168202091008425,
              0.0144154699519277,
              0.0263172760605812,
              0.0122129889205098,
              0.0169065743684769,
              0.0435698963701725,
              0.0393364131450653
            ],
            "angry": [
              0.00498873274773359,
              0.00575492065399885,
              0.00350346858613193,
              0.00213052821345627,
              0.00414547277614474,
              0.00215403013862669,
              0.00264002638868988,
              0.0123132662847638,
              0.0112406155094504
            ],
            "dangerous": [
              0.0337973088026047,
              0.0364954881370068,
              0.0490102879703045,
              0.035634208470583,
              0.0583896711468697,
              0.0341850928962231,
              0.0221068263053894,
              0.0390764735639095,
              0.0452394597232342
            ],
            "fiery": [
              0.0163785312324762,
              0.0202518291771412,
              0.0121498387306929,
              0.00809058174490929,
              0.0112352641299367,
              0.00701286597177386,
              0.00694507081061602,
              0.0246207155287266,
              0.0231201164424419
            ],
            "intense": [
              0.0662844479084015,
              0.0654215514659882,
              0.0543948449194431,
              0.0348973050713539,
              0.0576016269624233,
              0.0372505635023117,
              0.0332220979034901,
              0.0877621322870255,
              0.0896918103098869
            ],
            "passionate": [
              0.12691256403923,
              0.143751949071884,
              0.106192499399185,
              0.0623932667076588,
              0.0579119920730591,
              0.0761534869670868,
              0.0682701244950294,
              0.123016908764839,
              0.154972016811371
            ],
            "ponderous": [
              0.0648934841156006,
              0.129482537508011,
              0.150242254137993,
              0.116353318095207,
              0.173498496413231,
              0.120742402970791,
              0.0718229934573174,
              0.0735914334654808,
              0.0753247514367104
            ],
            "violent": [
              0.00553748616948724,
              0.0121941436082125,
              0.008942442946136,
              0.00516841653734446,
              0.00746304262429476,
              0.00526112783700228,
              0.00460204621776938,
              0.0210852697491646,
              0.0211530029773712
            ],
            "comedic": [
              0.0192748233675957,
              0.0241051614284515,
              0.0233902521431446,
              0.0754011571407318,
              0.0303910579532385,
              0.0321917310357094,
              0.0821051001548767,
              0.0611012242734432,
              0.0434804745018482
            ],
            "eccentric": [
              0.0265438798815012,
              0.0250937901437283,
              0.0263839736580849,
              0.063072606921196,
              0.0433855168521404,
              0.0338731929659843,
              0.0614190325140953,
              0.0501491390168667,
              0.0360763221979141
            ],
            "funny": [
              0.0158041436225176,
              0.0123256901279092,
              0.0119096441194415,
              0.0446964465081692,
              0.0139874024316669,
              0.0194304585456848,
              0.0540362037718296,
              0.0347268357872963,
              0.0203153565526009
            ],
            "mischievous": [
              0.0143713150173426,
              0.019107585772872,
              0.0143709750846028,
              0.0507398918271065,
              0.0355799123644829,
              0.0229466315358877,
              0.0710701122879982,
              0.0531669929623604,
              0.0381044335663319
            ],
            "quirky": [
              0.0408211909234524,
              0.043911274522543,
              0.0447471439838409,
              0.142856523394585,
              0.0835068076848984,
              0.0712815523147583,
              0.154103770852089,
              0.103508971631527,
              0.0686099752783775
            ],
            "whimsical": [
              0.0227050054818392,
              0.0320104099810123,
              0.024111608043313,
              0.0695621147751808,
              0.0375787504017353,
              0.0436194464564323,
              0.0938466340303421,
              0.0869773775339127,
              0.0627127289772034
            ],
            "boisterous": [
              0.0233245063573122,
              0.0264361184090376,
              0.0168459992855787,
              0.0264755897223949,
              0.019444614648819,
              0.0135162556543946,
              0.028044180944562,
              0.0335498787462711,
              0.0243579745292664
            ],
            "boingy": [
              0.0150467045605183,
              0.020916435867548,
              0.0113285118713975,
              0.0299520809203386,
              0.0173744428902864,
              0.0155480084940791,
              0.0340089499950409,
              0.038760844618082,
              0.0274375174194574
            ],
            "bright": [
              0.0201448928564787,
              0.0610342212021351,
              0.0209788326174021,
              0.053033784031868,
              0.0443565733730793,
              0.053333256393671,
              0.10724501311779,
              0.0837960466742516,
              0.0750315636396408
            ],
            "celebratory": [
              0.0121333645656705,
              0.0171078313142061,
              0.00629986543208361,
              0.00947466120123863,
              0.00702070584520698,
              0.00918833166360855,
              0.0181017480790615,
              0.0238433834165335,
              0.0207233708351851
            ],
            "cheerful": [
              0.0343851670622826,
              0.0286738984286785,
              0.0182346142828465,
              0.0405413955450058,
              0.0175724104046822,
              0.023330070078373,
              0.0603253170847893,
              0.0502117350697517,
              0.0370673909783363
            ],
            "excited": [
              0.0124189350754023,
              0.0260506682097912,
              0.0088826147839427,
              0.0145597606897354,
              0.0130436988547444,
              0.0108445100486279,
              0.0215834584087133,
              0.0349605157971382,
              0.0299384333193302
            ],
            "feelGood": [
              0.0995620861649513,
              0.0787814855575562,
              0.0579224601387978,
              0.0713274031877518,
              0.0350424163043499,
              0.0514802113175392,
              0.0695213153958321,
              0.0723885223269463,
              0.0636376664042473
            ],
            "fun": [
              0.0161809809505939,
              0.0247238222509623,
              0.0127366399392486,
              0.0350216440856457,
              0.0161251369863749,
              0.0194042529910803,
              0.0474732331931591,
              0.0451519303023815,
              0.0317805446684361
            ],
            "happy": [
              0.0250802673399448,
              0.032472986727953,
              0.0171602740883827,
              0.0373389758169651,
              0.0174790602177382,
              0.0250509213656187,
              0.0521401837468147,
              0.0492351800203323,
              0.0416390895843506
            ],
            "joyous": [
              0.0174254775047302,
              0.0205295830965042,
              0.00959906261414289,
              0.0163417458534241,
              0.0103945145383477,
              0.0133476220071316,
              0.0256388410925865,
              0.0280411615967751,
              0.0264786072075367
            ],
            "lighthearted": [
              0.0765031352639198,
              0.0479425229132175,
              0.0447230413556099,
              0.0745386183261871,
              0.0325909070670605,
              0.0416922345757484,
              0.0824142321944237,
              0.0679073557257652,
              0.0531919114291668
            ],
            "perky": [
              0.0184032097458839,
              0.0337435752153397,
              0.0160171315073967,
              0.0418597906827927,
              0.0283285621553659,
              0.0284758750349283,
              0.0545836314558983,
              0.0421199277043343,
              0.0369008742272854
            ],
            "playful": [
              0.0212098378688097,
              0.0333884283900261,
              0.0196127258241177,
              0.0606532581150532,
              0.0305036623030901,
              0.0289449151605368,
              0.0877131223678589,
              0.0776206329464912,
              0.0527408011257648
            ],
            "rollicking": [
              0.0290342699736357,
              0.025999017059803,
              0.0138228079304099,
              0.0164717026054859,
              0.0184387397021055,
              0.0100733423605561,
              0.0181930214166641,
              0.035907506942749,
              0.0281993206590414
            ],
            "upbeat": [
              0.0449638143181801,
              0.0657354667782784,
              0.0316479094326496,
              0.0442406386137009,
              0.0365225933492184,
              0.038746852427721,
              0.0634258463978767,
              0.0643176883459091,
              0.0545086897909641
            ],
            "calm": [
              0.352505475282669,
              0.273868590593338,
              0.433472961187363,
              0.298226714134216,
              0.276387065649033,
              0.406636476516724,
              0.273804217576981,
              0.260175317525864,
              0.333009839057922
            ],
            "contented": [
              0.260373055934906,
              0.211826294660568,
              0.228702679276466,
              0.245392516255379,
              0.127588346600533,
              0.230437397956848,
              0.211839094758034,
              0.164663180708885,
              0.173140496015549
            ],
            "dreamy": [
              0.34955158829689,
              0.349820047616959,
              0.449975848197937,
              0.262313604354858,
              0.264197945594788,
              0.460547029972076,
              0.31804370880127,
              0.371959924697876,
              0.493064314126968
            ],
            "introspective": [
              0.557257354259491,
              0.506048023700714,
              0.608572244644165,
              0.489826112985611,
              0.521452248096466,
              0.532598376274109,
              0.376523405313492,
              0.36699765920639,
              0.446105867624283
            ],
            "laidBack": [
              0.390561908483505,
              0.272770196199417,
              0.554831266403198,
              0.426771610975266,
              0.205729469656944,
              0.400020599365234,
              0.17575466632843,
              0.107842274010181,
              0.121557228267193
            ],
            "leisurely": [
              0.222316026687622,
              0.311481982469559,
              0.422195851802826,
              0.309911757707596,
              0.271053194999695,
              0.427366405725479,
              0.220228597521782,
              0.206754848361015,
              0.263880968093872
            ],
            "lyrical": [
              0.111732460558414,
              0.0822002664208412,
              0.084697388112545,
              0.0587344840168953,
              0.0347928777337074,
              0.0672314614057541,
              0.0614319033920765,
              0.0967386960983276,
              0.137033775448799
            ],
            "peaceful": [
              0.467347323894501,
              0.276128858327866,
              0.451818197965622,
              0.284301668405533,
              0.193634703755379,
              0.385654181241989,
              0.247695952653885,
              0.241960436105728,
              0.322281718254089
            ],
            "quiet": [
              0.394978553056717,
              0.208488613367081,
              0.420206099748611,
              0.237420916557312,
              0.216871693730354,
              0.284560084342957,
              0.248943373560905,
              0.221589982509613,
              0.266504645347595
            ],
            "relaxed": [
              0.617205142974854,
              0.467109709978104,
              0.641899287700653,
              0.542325913906097,
              0.341845393180847,
              0.537839889526367,
              0.350852876901627,
              0.328411728143692,
              0.365668207406998
            ],
            "serene": [
              0.503309786319733,
              0.331759065389633,
              0.467510759830475,
              0.289054870605469,
              0.224723860621452,
              0.415535748004913,
              0.289714932441711,
              0.276951730251312,
              0.340942651033401
            ],
            "soothing": [
              0.332420736551285,
              0.157529532909393,
              0.240710571408272,
              0.172280564904213,
              0.125092968344688,
              0.231907576322556,
              0.157250165939331,
              0.15633162856102,
              0.188507705926895
            ],
            "spiritual": [
              0.217715948820114,
              0.140602216124535,
              0.202305361628532,
              0.147679358720779,
              0.213167726993561,
              0.237621203064919,
              0.201273426413536,
              0.167447566986084,
              0.201761275529861
            ],
            "tranquil": [
              0.352638781070709,
              0.245651140809059,
              0.416493743658066,
              0.256548881530762,
              0.212757468223572,
              0.379189610481262,
              0.23600597679615,
              0.208738818764687,
              0.270048946142197
            ],
            "bittersweet": [
              0.590703070163727,
              0.517780840396881,
              0.604506075382233,
              0.524205565452576,
              0.508442223072052,
              0.540139496326447,
              0.45107427239418,
              0.32831084728241,
              0.418729364871979
            ],
            "blue": [
              0.615663051605225,
              0.408665478229523,
              0.636360645294189,
              0.521066188812256,
              0.479619473218918,
              0.532026469707489,
              0.389106810092926,
              0.243156686425209,
              0.309938132762909
            ],
            "depressing": [
              0.26685506105423,
              0.172515019774437,
              0.437859863042831,
              0.178508162498474,
              0.240821540355682,
              0.259896636009216,
              0.103811107575893,
              0.0851739197969437,
              0.123090170323849
            ],
            "gloomy": [
              0.154239997267723,
              0.139191538095474,
              0.258957982063293,
              0.168712243437767,
              0.300893396139145,
              0.234248489141464,
              0.112977206707001,
              0.104676984250546,
              0.138277918100357
            ],
            "heavy": [
              0.241885036230087,
              0.141676217317581,
              0.190362080931664,
              0.100328110158443,
              0.172497063875198,
              0.119690082967281,
              0.0827494859695435,
              0.134706944227219,
              0.164878651499748
            ],
            "lonely": [
              0.577837765216827,
              0.508024334907532,
              0.668165564537048,
              0.554260075092316,
              0.553630292415619,
              0.578738808631897,
              0.472275704145432,
              0.275461941957474,
              0.369641751050949
            ],
            "melancholic": [
              0.538057923316956,
              0.4721999168396,
              0.594001054763794,
              0.438541620969772,
              0.488982766866684,
              0.506026268005371,
              0.346922308206558,
              0.301073729991913,
              0.39585354924202
            ],
            "mournful": [
              0.366257935762405,
              0.255200505256653,
              0.495841205120087,
              0.267488747835159,
              0.293422490358353,
              0.340294539928436,
              0.176149189472198,
              0.150145575404167,
              0.219555974006653
            ],
            "poignant": [
              0.255534708499908,
              0.270585626363754,
              0.333297789096832,
              0.157016232609749,
              0.254523187875748,
              0.25708144903183,
              0.160992458462715,
              0.175702020525932,
              0.254073917865753
            ],
            "sad": [
              0.398628503084183,
              0.312241494655609,
              0.507076621055603,
              0.249286219477654,
              0.312261283397675,
              0.341093778610229,
              0.188692852854729,
              0.189329981803894,
              0.272127777338028
            ],
            "frightening": [
              0.0137646719813347,
              0.0201973728835583,
              0.0218966007232666,
              0.0260708350688219,
              0.0397177003324032,
              0.0300763938575983,
              0.0257539320737123,
              0.0393486805260181,
              0.0503106154501438
            ],
            "horror": [
              0.00451125297695398,
              0.00773705495521426,
              0.00852780509740114,
              0.00997331086546183,
              0.0224057659506798,
              0.0140990205109119,
              0.0136744361370802,
              0.0218013729900122,
              0.0278049930930138
            ],
            "menacing": [
              0.061025008559227,
              0.0668685138225555,
              0.0989203751087189,
              0.0950460135936737,
              0.1505097001791,
              0.0948680266737938,
              0.0770757496356964,
              0.0897157266736031,
              0.105611264705658
            ],
            "nightmarish": [
              0.0115458145737648,
              0.00987742561846972,
              0.0157035272568464,
              0.0169389024376869,
              0.0263064410537481,
              0.0178561676293612,
              0.015484600327909,
              0.0214635375887156,
              0.0258712284266949
            ],
            "ominous": [
              0.0666279643774033,
              0.0754942521452904,
              0.0890237465500832,
              0.0645745098590851,
              0.20296935737133,
              0.0829432755708694,
              0.0623550526797771,
              0.118046425282955,
              0.143136546015739
            ],
            "panicStricken": [
              0.00704730441793799,
              0.00625207368284464,
              0.00544937048107386,
              0.0044332598336041,
              0.00920424517244101,
              0.00347480527125299,
              0.00507870130240917,
              0.0148484790697694,
              0.013749485835433
            ],
            "scary": [
              0.0136649468913674,
              0.0155387381091714,
              0.0205069705843925,
              0.0239343643188477,
              0.0423485711216927,
              0.0281110685318708,
              0.0225985627621412,
              0.0292490310966969,
              0.0381681807339191
            ],
            "concerned": [
              0.196921646595001,
              0.179364398121834,
              0.270760953426361,
              0.171856611967087,
              0.298115223646164,
              0.218722730875015,
              0.151866227388382,
              0.140254452824593,
              0.151268035173416
            ],
            "determined": [
              0.0607694573700428,
              0.124344743788242,
              0.0748545527458191,
              0.0755346864461899,
              0.0976893976330757,
              0.0714278295636177,
              0.0700889527797699,
              0.0868463665246964,
              0.0815565213561058
            ],
            "dignified": [
              0.046105794608593,
              0.0657629817724228,
              0.0358288586139679,
              0.0349807254970074,
              0.0285259764641523,
              0.0471106916666031,
              0.0436413995921612,
              0.0567566901445389,
              0.0642141625285149
            ],
            "emotional": [
              0.238528460264206,
              0.279583781957626,
              0.272982150316238,
              0.130717515945435,
              0.171238958835602,
              0.220583260059357,
              0.153204724192619,
              0.169596612453461,
              0.22194804251194
            ],
            "noble": [
              0.0294872764497995,
              0.0377862118184566,
              0.0200106538832188,
              0.020084772258997,
              0.0135504780337214,
              0.0274037159979343,
              0.0258746054023504,
              0.0414659455418587,
              0.0477932505309582
            ],
            "serious": [
              0.308204472064972,
              0.296255379915237,
              0.363335967063904,
              0.247160285711288,
              0.39485439658165,
              0.289917588233948,
              0.198193401098251,
              0.198131337761879,
              0.214764982461929
            ],
            "solemn": [
              0.0810312405228615,
              0.112397499382496,
              0.107385456562042,
              0.0817511156201363,
              0.0922368392348289,
              0.120008729398251,
              0.0878017917275429,
              0.0975879952311516,
              0.119815953075886
            ],
            "thoughtful": [
              0.424870789051056,
              0.381746083498001,
              0.506632924079895,
              0.369782477617264,
              0.522836267948151,
              0.484024196863174,
              0.358578652143478,
              0.273073792457581,
              0.32414299249649
            ],
            "cool": [
              0.0627621784806252,
              0.0607232265174389,
              0.0544379092752934,
              0.0506130456924438,
              0.041758980602026,
              0.0458668656647205,
              0.0374277755618095,
              0.0520783960819244,
              0.0478653348982334
            ],
            "seductive": [
              0.108015649020672,
              0.0846068933606148,
              0.0858490169048309,
              0.0897443518042564,
              0.0761035308241844,
              0.0779484435915947,
              0.105120770633221,
              0.110633797943592,
              0.120727486908436
            ],
            "sexy": [
              0.0525719076395035,
              0.0522493235766888,
              0.0497669279575348,
              0.0438447371125221,
              0.0361168533563614,
              0.0422282516956329,
              0.04757309705019,
              0.064098484814167,
              0.0682761743664742
            ],
            "adventurous": [
              0.0230596922338009,
              0.0269668810069561,
              0.0133400987833738,
              0.0109623465687037,
              0.0137128802016377,
              0.012809744104743,
              0.0145009011030197,
              0.0345911979675293,
              0.0343533083796501
            ],
            "confident": [
              0.09726382791996,
              0.156356990337372,
              0.0809494629502296,
              0.0813108757138252,
              0.0623656287789345,
              0.0786469057202339,
              0.0830768942832947,
              0.117601431906223,
              0.102405995130539
            ],
            "courageous": [
              0.0190953053534031,
              0.0241505112498999,
              0.0114945387467742,
              0.00751812616363168,
              0.0081973522901535,
              0.0102448714897037,
              0.00968211237341166,
              0.0234962590038776,
              0.0235291235148907
            ],
            "resolute": [
              0.0618976019322872,
              0.108363024890423,
              0.0575005710124969,
              0.0477824844419956,
              0.060070376843214,
              0.0496564991772175,
              0.0451504960656166,
              0.0750525519251823,
              0.068203516304493
            ],
            "energetic": [
              0.0205956045538187,
              0.0449945293366909,
              0.0169163960963488,
              0.0157888121902943,
              0.0237152893096209,
              0.0125889657065272,
              0.0191660039126873,
              0.0460465736687183,
              0.037021741271019
            ],
            "epic": [
              0.00628686929121614,
              0.0180536136031151,
              0.00663729943335056,
              0.00347548071295023,
              0.00648697605356574,
              0.00961481872946024,
              0.00643682572990656,
              0.0186638925224543,
              0.0251130182296038
            ],
            "exciting": [
              0.0247981734573841,
              0.0310766287147999,
              0.0124929072335362,
              0.0111564612016082,
              0.0142027847468853,
              0.0103282583877444,
              0.0145574938505888,
              0.0435264185070992,
              0.0403813682496548
            ],
            "exhilarating": [
              0.0217168349772692,
              0.0323156118392944,
              0.0147720314562321,
              0.014136616140604,
              0.0101400977000594,
              0.0135728772729635,
              0.0153033249080181,
              0.0280833449214697,
              0.0295012015849352
            ],
            "heroic": [
              0.00704497052356601,
              0.0115391938015819,
              0.00399766396731138,
              0.00307390652596951,
              0.00293878139927983,
              0.00536995194852352,
              0.00476426770910621,
              0.0125505346804857,
              0.0144765675067902
            ],
            "majestic": [
              0.00605515390634537,
              0.0135824745520949,
              0.00386071391403675,
              0.00366332847625017,
              0.00325793423689902,
              0.00766818830743432,
              0.00707495864480734,
              0.0155943846330047,
              0.0200588721781969
            ],
            "powerful": [
              0.0107075208798051,
              0.035743460059166,
              0.0145236132666469,
              0.0119643285870552,
              0.0171660389751196,
              0.0153156844899058,
              0.0138310138136148,
              0.0298514068126678,
              0.0302806310355663
            ],
            "prestigious": [
              0.011481998488307,
              0.0171099305152893,
              0.0065416544675827,
              0.0084022730588913,
              0.00933555234223604,
              0.0117119811475277,
              0.0114023787900805,
              0.0146932462230325,
              0.0157947242259979
            ],
            "relentless": [
              0.0489787571132183,
              0.0506998524069786,
              0.0380068607628345,
              0.0277225505560637,
              0.0477126836776733,
              0.0234834589064121,
              0.0244773682206869,
              0.0615329928696156,
              0.0529572404921055
            ],
            "strong": [
              0.0199255775660276,
              0.0521833747625351,
              0.0230333469808102,
              0.0164961833506823,
              0.0214060712605715,
              0.020483760163188,
              0.0155129060149193,
              0.0347469002008438,
              0.0341577082872391
            ],
            "triumphant": [
              0.00603482080623507,
              0.0137125449255109,
              0.0033327981363982,
              0.00355392321944237,
              0.00316931423731148,
              0.0062518585473299,
              0.00605180626735091,
              0.0151259023696184,
              0.0156183252111077
            ],
            "victorious": [
              0.00634745135903358,
              0.0148722622543573,
              0.00438662525266409,
              0.00338643253780901,
              0.00397444423288107,
              0.00545222265645862,
              0.0047446577809751,
              0.0159014202654362,
              0.0163666736334562
            ],
            "delicate": [
              0.146245390176773,
              0.12564405798912,
              0.124196596443653,
              0.11663942784071,
              0.146952852606773,
              0.163055613636971,
              0.196013182401657,
              0.201674416661263,
              0.23598700761795
            ],
            "graceful": [
              0.0649223625659943,
              0.0724174231290817,
              0.0459209680557251,
              0.0448706932365894,
              0.0377804636955261,
              0.0631338432431221,
              0.0717830881476402,
              0.107940658926964,
              0.140482559800148
            ],
            "hopeful": [
              0.11308266222477,
              0.152091845870018,
              0.091481976211071,
              0.0617408715188503,
              0.0894319266080856,
              0.115066677331924,
              0.102195113897324,
              0.136961624026299,
              0.153966128826141
            ],
            "innocent": [
              0.0723488256335258,
              0.0635749399662018,
              0.0570222698152065,
              0.0838226601481438,
              0.0653296709060669,
              0.0897967293858528,
              0.163595020771027,
              0.146034866571426,
              0.132044985890388
            ],
            "intimate": [
              0.224887564778328,
              0.207859873771667,
              0.277558445930481,
              0.198715656995773,
              0.173568978905678,
              0.253117978572845,
              0.246208235621452,
              0.247239038348198,
              0.281839162111282
            ],
            "kind": [
              0.101695254445076,
              0.0556245371699333,
              0.0536165907979012,
              0.0578288733959198,
              0.0397221408784389,
              0.0559506677091122,
              0.0704712048172951,
              0.0888433083891869,
              0.0873740166425705
            ],
            "light": [
              0.192225500941277,
              0.184590324759483,
              0.189855188131332,
              0.22262978553772,
              0.197215884923935,
              0.213547930121422,
              0.263212263584137,
              0.230891987681389,
              0.230117425322533
            ],
            "loving": [
              0.197224736213684,
              0.119324661791325,
              0.138588473200798,
              0.0625419393181801,
              0.0529109239578247,
              0.100785434246063,
              0.0840050056576729,
              0.127426460385323,
              0.159195646643639
            ],
            "nostalgic": [
              0.324360221624374,
              0.40002977848053,
              0.511717259883881,
              0.347638368606567,
              0.29779726266861,
              0.419467628002167,
              0.29900386929512,
              0.269364684820175,
              0.352117151021957
            ],
            "reflective": [
              0.425638794898987,
              0.447271078824997,
              0.511145412921906,
              0.324028849601746,
              0.390193700790405,
              0.439201861619949,
              0.292985618114471,
              0.343031525611877,
              0.431114047765732
            ],
            "romantic": [
              0.153099089860916,
              0.122670367360115,
              0.109582416713238,
              0.0593892969191074,
              0.0482738688588142,
              0.0871576592326164,
              0.0918175652623177,
              0.1484285145998,
              0.199812486767769
            ],
            "sentimental": [
              0.209891125559807,
              0.203445851802826,
              0.218433663249016,
              0.124964982271194,
              0.111751556396484,
              0.168028026819229,
              0.172735884785652,
              0.192701429128647,
              0.249104261398315
            ],
            "soft": [
              0.103710681200027,
              0.136216357350349,
              0.172389894723892,
              0.117212258279324,
              0.127510160207748,
              0.18581759929657,
              0.15409728884697,
              0.155426308512688,
              0.192556828260422
            ],
            "sweet": [
              0.0460041873157024,
              0.0557719208300114,
              0.0407879315316677,
              0.0460896678268909,
              0.0460680164396763,
              0.0616320408880711,
              0.107643470168114,
              0.136851742863655,
              0.129904523491859
            ],
            "tender": [
              0.223300933837891,
              0.159277573227882,
              0.168686732649803,
              0.102527424693108,
              0.0962567254900932,
              0.153068244457245,
              0.152541548013687,
              0.199141144752502,
              0.234960913658142
            ],
            "warm": [
              0.388527512550354,
              0.293394327163696,
              0.300156652927399,
              0.187899231910706,
              0.170480847358704,
              0.257008761167526,
              0.206233307719231,
              0.264040023088455,
              0.308111876249313
            ],
            "anthemic": [
              0.00771150551736355,
              0.0192805007100105,
              0.00483456999063492,
              0.00372007349506021,
              0.0055773239582777,
              0.00829505920410156,
              0.00721335737034678,
              0.019060704857111,
              0.0200976803898811
            ],
            "aweInspiring": [
              0.0248116459697485,
              0.0302424095571041,
              0.0107673844322562,
              0.007815882563591,
              0.0138370022177696,
              0.0189331918954849,
              0.0140800662338734,
              0.0267498735338449,
              0.0314722247421741
            ],
            "euphoric": [
              0.00684211729094386,
              0.0167577303946018,
              0.00580714596435428,
              0.00518335448578,
              0.00709640281274915,
              0.0086386427283287,
              0.0101031921803951,
              0.0174642372876406,
              0.0200042016804218
            ],
            "inspirational": [
              0.0483140386641026,
              0.0729029551148415,
              0.0253043193370104,
              0.020203024148941,
              0.0274973958730698,
              0.0402767285704613,
              0.0391078516840935,
              0.0594160929322243,
              0.0612559653818607
            ],
            "motivational": [
              0.0299964025616646,
              0.0484611615538597,
              0.01644023694098,
              0.0149714583531022,
              0.0237213037908077,
              0.0205627307295799,
              0.0235351342707872,
              0.042346004396677,
              0.0358278155326843
            ],
            "optimistic": [
              0.0719837322831154,
              0.0987452045083046,
              0.0430312342941761,
              0.0588193498551846,
              0.0423852019011974,
              0.0635243579745293,
              0.0834284052252769,
              0.0853912457823753,
              0.0805758163332939
            ],
            "positive": [
              0.137671872973442,
              0.100674264132977,
              0.0561836883425713,
              0.0703594982624054,
              0.0577847398817539,
              0.0648351460695267,
              0.0909025073051453,
              0.104911558330059,
              0.0969099551439285
            ],
            "proud": [
              0.0551648996770382,
              0.0580087527632713,
              0.0284931864589453,
              0.0268281083554029,
              0.0165112502872944,
              0.029313787817955,
              0.028156541287899,
              0.0471227765083313,
              0.0483225733041763
            ],
            "soaring": [
              0.0391125418245792,
              0.0524377040565014,
              0.0228541512042284,
              0.0184785798192024,
              0.024343054741621,
              0.03416957706213,
              0.030780179426074,
              0.0495441555976868,
              0.0580105744302273
            ],
            "uplifting": [
              0.0522946864366531,
              0.0750135183334351,
              0.0269314162433147,
              0.0229819379746914,
              0.0259528737515211,
              0.0378697924315929,
              0.0444629602134228,
              0.0673772692680359,
              0.0710838213562965
            ]
          }
        }
      }
    },
    "augmentedKeywords": {
      "__typename": "AugmentedKeywords",
      "keywords": [
        {
          "keyword": "thoughtful",
          "weight": 2.88
        },
        {
          "keyword": "reflective",
          "weight": 2.74
        },
        {
          "keyword": "contemplative",
          "weight": 2.72
        },
        {
          "keyword": "sentimental",
          "weight": 2.69
        },
        {
          "keyword": "calm",
          "weight": 2.66
        },
        {
          "keyword": "introspective",
          "weight": 2.57
        },
        {
          "keyword": "dreamy",
          "weight": 2.55
        },
        {
          "keyword": "pensive",
          "weight": 2.46
        },
        {
          "keyword": "tender",
          "weight": 2.45
        },
        {
          "keyword": "relaxed",
          "weight": 2.45
        },
        {
          "keyword": "tranquil",
          "weight": 2.31
        },
        {
          "keyword": "touching",
          "weight": 2.27
        },
        {
          "keyword": "soft",
          "weight": 2.25
        },
        {
          "keyword": "peaceful",
          "weight": 2.18
        },
        {
          "keyword": "feeling",
          "weight": 2.17
        },
        {
          "keyword": "melancholic",
          "weight": 2.16
        },
        {
          "keyword": "smooth",
          "weight": 2.15
        },
        {
          "keyword": "sorrowful",
          "weight": 2.14
        },
        {
          "keyword": "emotional",
          "weight": 2.12
        },
        {
          "keyword": "chilled",
          "weight": 2.12
        }
      ]
    },
    "brandValues": {
      "__typename": "BrandValuesError",
      "message": "Your account is not eligible for brand values. Contact us via sales@cyanite.ai if you want to upgrade your account.",
      "code": "notEligible"
    }
  }
}